{
  "schemaVersion": 1,
  "id": "journeyroute",
  "version": "${version}",

  "name": "JourneyRoute",
  "description": "A mod that helps you find your way",
  "authors": [
    "Encodeous"
  ],
  "contact": {
    "homepage": "https://fabricmc.net/",
    "sources": "https://github.com/FabricMC/fabric-example-mod"
  },

  "license": "MIT",
  "icon": "assets/journeyroute/icon.png",

  "environment": "*",
  "entrypoints": {
    "main": [
      "ca.encodeous.journeyroute.JourneyRoute"
    ],
    "journeymap": [
      "ca.encodeous.journeyroute.client.plugin.JourneyMapPlugin"
    ]
  },
  "mixins": [
    "journeyroute.mixins.json"
  ],
  "accessWidener": "journeyroute.accesswidener",
  "depends": {
    "fabricloader": ">=0.13.3",
    "fabric": "*",
    "minecraft": "1.18.x",
    "java": ">=17"
  }
}
